{
  "logo": {
    "link": "https://github.com/ufrpe-devs",
    "image": "https://i.imgur.com/irkDJMm.png"
  },
  "header": "[DEV] UFRPE Devs - Mailer",
  "metadata": {
    "link": ""
  },
  "footer": {
    "text": "UFRPE Devs"
  },
  "theme": {
    "colors": {
      "background": "#0E1117",
      "backgroundSecondary": "#161B22",
      "backgroundTertiary": "#FFFFFF",
      "brand": "#122E4B",
      "textLight": "#FFFFFF",
      "textHighlight": "#3AAAFF",
      "textDark": "#363636",
      "border": "#CCCCCC"
    }
  }
}
